framedwindow.py
pybuildpush.py
samples.py
jmcursed-0.130.dist-info/METADATA
jmcursed-0.130.dist-info/WHEEL
jmcursed-0.130.dist-info/top_level.txt
jmcursed-0.130.dist-info/RECORD
