Metadata-Version: 2.1
Name: jmcursed
Version: 0.130
Summary: simple window with ncurses
Home-page: http://xframe.vixal.net
Author: jimferd
Author-email: jimferd@gmail.com
License: MIT
Platform: UNKNOWN
